HuggingChatAPI/Errors.py
HuggingChatAPI/HuggingChatAPI.py
HuggingChatAPI/Warnings.py
HuggingChatAPI/__init__.py
HuggingChatAPI/utils.py
HuggingChatAPI-1.2.0.dist-info/METADATA
HuggingChatAPI-1.2.0.dist-info/WHEEL
HuggingChatAPI-1.2.0.dist-info/top_level.txt
HuggingChatAPI-1.2.0.dist-info/RECORD
