Metadata-Version: 2.1
Name: HuggingChatAPI
Version: 1.2.0
Summary: The project is an unofficial API for the site huggingface.co/chat.
Home-page: https://github.com/ILYXAAA/HuggingChatAPI
Author: ILYXAAA
Author-email: ilyagolybnichev@gmail.com
Project-URL: GitHub, https://github.com/ILYXAAA/HuggingChatAPI
Keywords: files HuggingChatAPI API AI Bot
Classifier: Programming Language :: Python :: 3.10
Classifier: Operating System :: OS Independent
Requires-Python: >=3.6
Requires-Dist: googletrans ==4.0.0-rc1
Requires-Dist: Pygments
Requires-Dist: requests
Requires-Dist: urllib3
